sbapi_dev/__init__.py
sbapi_dev/auth.py
sbapi_dev/base.py
sbapi_dev/bolt.py
sbapi_dev/client.py
sbapi_dev/database.py
sbapi_dev/exceptions.py
sbapi_dev/find.py
sbapi_dev/site.py
sbapi_dev-0.1.0.dist-info/licenses/LICENSE
sbapi_dev-0.1.0.dist-info/METADATA
sbapi_dev-0.1.0.dist-info/WHEEL
sbapi_dev-0.1.0.dist-info/top_level.txt
sbapi_dev-0.1.0.dist-info/RECORD
