Metadata-Version: 2.4
Name: sbapi-dev
Version: 0.1.0
Summary: Python wrapper for the Servebolt API
Author-email: Oskar <your-email@example.com>
License: MIT
Requires-Python: >=3.8
License-File: LICENSE
Requires-Dist: requests
Requires-Dist: rich
Dynamic: license-file
